flask_task.py
flask_task-1.0.dist-info/LICENSE
flask_task-1.0.dist-info/METADATA
flask_task-1.0.dist-info/WHEEL
flask_task-1.0.dist-info/top_level.txt
flask_task-1.0.dist-info/RECORD
