Metadata-Version: 2.1
Name: flask-task
Version: 1.0
Summary: Basic flask task
Home-page: https://github.com/FranciscoCarbonell/flask-task
Author: Francisco Carbonell
Author-email: francabezo@gmail.com
License: MIT
Platform: any
Requires-Dist: Flask
